<?xml version="1.0" encoding="utf-8"?>
<LevelConfig xmlns:xsi="http://www.w3.org/2001/XMLSchema-instance" xmlns:xsd="http://www.w3.org/2001/XMLSchema">
  <ID>0</ID>
  <blockArrangement>
    <string>CityBlock2,CityBlock5</string>
    <string>CityBlock4,CityBlock1</string>
    <string>CityBlock1,CityBlock2</string>
    <string>CityBlock2,CityBlock5</string>
    <string>CityBlock1,CityBlock2</string>
  </blockArrangement>
  <waveSpawnList>
  <WaveSpawn>
    <name>CircleWave</name>
    <startPosition>
      <x>13.3449688</x>
      <y>13.74516</y>
      <z>17.7668877</z>
    </startPosition>
  </WaveSpawn>
  <WaveSpawn>
    <name>CircleWave</name>
    <startPosition>
      <x>27.7593575</x>
      <y>13.74516</y>
      <z>28.19718</z>
    </startPosition>
  </WaveSpawn>
  <WaveSpawn>
    <name>VerticalWave</name>
    <startPosition>
      <x>16.8610744</x>
      <y>13.74516</y>
      <z>34.3435059</z>
    </startPosition>
  </WaveSpawn>
  <WaveSpawn>
    <name>VShapeKamikazeWave</name>
    <startPosition>
      <x>20.591404</x>
      <y>13.74516</y>
      <z>45.33531</z>
    </startPosition>
  </WaveSpawn>
  </waveSpawnList>
   <bossName>Boss0</bossName>
  <pickUpSpawnList>
    <PickUpSpawn>
      <name>HealthPickup</name>
      <startPosition>
        <x>-2</x>
        <z>35</z>
      </startPosition>	  
    </PickUpSpawn>	
    <PickUpSpawn>
      <name>GunSpreadPickup</name>
      <startPosition>
        <x>2</x>
        <z>45</z>
      </startPosition>	  
    </PickUpSpawn>
  </pickUpSpawnList>
  <wavesLoopCount>6</wavesLoopCount>
  <loopPickUps>true</loopPickUps>
  <loopPickUpsDelay>10</loopPickUpsDelay>
  <spawnEnemies>true</spawnEnemies>
  <spawnBlocks>true</spawnBlocks>
  <spawnPickups>true</spawnPickups>  
  <spawnTurrets>false</spawnTurrets> 
  <turretRoundsPerMinute>30</turretRoundsPerMinute>
</LevelConfig>